c302/CompareMain.py
c302/ConnectomeReader.py
c302/Cook2019DataReader.py
c302/Cook2019HermReader.py
c302/LEMS_c302_TEMPLATE.xml
c302/NeuroMLUtilities.py
c302/OpenWormReader.py
c302/SpreadsheetDataReader.py
c302/UpdatedSpreadsheetDataReader.py
c302/UpdatedSpreadsheetDataReader2.py
c302/VarshneyDataReader.py
c302/W_SpreadsheetDataReader.py
c302/WhiteDataReader.py
c302/White_A.py
c302/White_L4.py
c302/White_whole.py
c302/WitvlietDataReader1.py
c302/WitvlietDataReader2.py
c302/WormNeuroAtlasReader.py
c302/__init__.py
c302/__version__.py
c302/analyse.py
c302/backers.py
c302/bioparameters.py
c302/c302_FW.py
c302/c302_Full.py
c302/c302_IClamp.py
c302/c302_IClampMuscle.py
c302/c302_MultiSyns.py
c302/c302_MuscleTest.py
c302/c302_Muscles.py
c302/c302_MusclesSine.py
c302/c302_Oscillator.py
c302/c302_OscillatorM.py
c302/c302_Pharyngeal.py
c302/c302_RIA.py
c302/c302_Social.py
c302/c302_Syns.py
c302/c302_TapWithdrawal.py
c302/c302_TargetMuscle.py
c302/c302_info.py
c302/c302_utils.py
c302/cell_B.xml
c302/cell_C.xml
c302/cell_W2D.xml
c302/cell_X.xml
c302/custom_muscle_components.xml
c302/custom_synapses.xml
c302/gen_graph.py
c302/parameters_A.py
c302/parameters_B.py
c302/parameters_BC1.py
c302/parameters_C.py
c302/parameters_C0.py
c302/parameters_C1.py
c302/parameters_C2.py
c302/parameters_D.py
c302/parameters_D1.py
c302/parameters_W2D.py
c302/runAndPlot.py
c302/NeuroML2/ADAL.cell.nml
c302/NeuroML2/ADAR.cell.nml
c302/NeuroML2/ADEL.cell.nml
c302/NeuroML2/ADER.cell.nml
c302/NeuroML2/ADFL.cell.nml
c302/NeuroML2/ADFR.cell.nml
c302/NeuroML2/ADLL.cell.nml
c302/NeuroML2/ADLR.cell.nml
c302/NeuroML2/AFDL.cell.nml
c302/NeuroML2/AFDR.cell.nml
c302/NeuroML2/AIAL.cell.nml
c302/NeuroML2/AIAR.cell.nml
c302/NeuroML2/AIBL.cell.nml
c302/NeuroML2/AIBR.cell.nml
c302/NeuroML2/AIML.cell.nml
c302/NeuroML2/AIMR.cell.nml
c302/NeuroML2/AINL.cell.nml
c302/NeuroML2/AINR.cell.nml
c302/NeuroML2/AIYL.cell.nml
c302/NeuroML2/AIYR.cell.nml
c302/NeuroML2/AIZL.cell.nml
c302/NeuroML2/AIZR.cell.nml
c302-0.10.1.dist-info/licenses/LICENSE
c302-0.10.1.dist-info/METADATA
c302-0.10.1.dist-info/WHEEL
c302-0.10.1.dist-info/entry_points.txt
c302-0.10.1.dist-info/top_level.txt
c302-0.10.1.dist-info/RECORD
