Metadata-Version: 2.4
Name: c302
Version: 0.10.1
Summary: c302 is a framework for generating models of the worm C. elegans
Home-page: http://github.com/openworm/c302
Download-URL: https://github.com/openworm/c302/archive/master.zip
Author: Padraig Gleeson and OpenWorm contributors
Author-email: p.gleeson@gmail.com
License: MIT
Classifier: Intended Audience :: Science/Research
Classifier: License :: OSI Approved :: MIT License
Classifier: Natural Language :: English
Classifier: Operating System :: OS Independent
Classifier: Programming Language :: Python :: 3
Classifier: Topic :: Scientific/Engineering
License-File: LICENSE
Requires-Dist: numpy
Requires-Dist: xlrd
Requires-Dist: xlwt
Requires-Dist: pyNeuroML>=1.3.15
Requires-Dist: WormNeuroAtlas
Requires-Dist: cect>=0.2.5
Dynamic: author
Dynamic: author-email
Dynamic: classifier
Dynamic: description
Dynamic: download-url
Dynamic: home-page
Dynamic: license
Dynamic: license-file
Dynamic: requires-dist
Dynamic: summary
